station/__init__.py
station/core.py
station_core-1.0.1.dist-info/METADATA
station_core-1.0.1.dist-info/WHEEL
station_core-1.0.1.dist-info/top_level.txt
station_core-1.0.1.dist-info/RECORD
