Metadata-Version: 2.1
Name: station-core
Version: 1.0.1
Summary: Station core module
License: Station Corp Software License Agreement
